effect_log/__init__.py
effect_log/logger.py
effect_log/middleware.py
effect_log/types.py
effect_log/writers.py
effect_log-0.0.1.dist-info/METADATA
effect_log-0.0.1.dist-info/WHEEL
effect_log-0.0.1.dist-info/licenses/LICENSE
effect_log-0.0.1.dist-info/RECORD
