Metadata-Version: 2.4
Name: effect-log
Version: 0.0.1
Summary: Functional structured logging with composable effects
License-Expression: MIT
License-File: LICENSE
Keywords: logging,functional,structured,effect,immutable
Author: Effect-Py Organization
Author-email: maintainers@effect-py.org
Maintainer: Effect-Py Organization
Maintainer-email: maintainers@effect-py.org
Requires-Python: >=3.11
Classifier: Development Status :: 4 - Beta
Classifier: Intended Audience :: Developers
Classifier: Operating System :: OS Independent
Classifier: Programming Language :: Python :: 3
Classifier: Programming Language :: Python :: 3.11
Classifier: Programming Language :: Python :: 3.12
Classifier: Programming Language :: Python :: 3.13
Classifier: Topic :: Software Development :: Libraries :: Python Modules
Classifier: Topic :: System :: Logging
Classifier: Typing :: Typed
Requires-Dist: starlette (>=0.47.2)
Project-URL: Documentation, https://github.com/effect-py/log/blob/main/README.md
Project-URL: Homepage, https://github.com/effect-py/log
Project-URL: Repository, https://github.com/effect-py/log
